hello.py
ams_a-0.0.1.dist-info/DESCRIPTION.rst
ams_a-0.0.1.dist-info/METADATA
ams_a-0.0.1.dist-info/RECORD
ams_a-0.0.1.dist-info/WHEEL
ams_a-0.0.1.dist-info/metadata.json
ams_a-0.0.1.dist-info/top_level.txt
